cbbuild/__init__.py
cbbuild/util/__init__.py
cbbuild/util/git.py
cbbuild/util/update_tool_check.py
cbbuild_util-0.7.0.dist-info/METADATA
cbbuild_util-0.7.0.dist-info/WHEEL
cbbuild_util-0.7.0.dist-info/RECORD
