Metadata-Version: 2.3
Name: cbbuild-util
Version: 0.7.0
Summary: Couchbase Build Team utilities package
Author-email: Couchbase Build Team <build-team@couchbase.com>
License: Apache License, Version 2.0
Requires-Python: <4,>=3.10
Requires-Dist: dulwich>=0.19.9
Requires-Dist: lxml>=3.8.0
Requires-Dist: requests>=2.20.0
